django_no_hot_reload_mod/__init__.py
django_no_hot_reload_mod/src/__init__.py
django_no_hot_reload_mod/src/code_modifier/__init__.py
django_no_hot_reload_mod/src/code_modifier/admin.py
django_no_hot_reload_mod/src/code_modifier/apps.py
django_no_hot_reload_mod/src/code_modifier/forms.py
django_no_hot_reload_mod/src/code_modifier/models.py
django_no_hot_reload_mod/src/code_modifier/urls.py
django_no_hot_reload_mod/src/code_modifier/utils.py
django_no_hot_reload_mod/src/code_modifier/views.py
django_no_hot_reload_mod/src/code_modifier/migrations/__init__.py
django_no_hot_reload_mod/src/code_modifier/templates/code_modifier/code_blocks.html
django_no_hot_reload_mod-0.0.2.1.dist-info/METADATA
django_no_hot_reload_mod-0.0.2.1.dist-info/WHEEL
django_no_hot_reload_mod-0.0.2.1.dist-info/licenses/LICENSE
django_no_hot_reload_mod-0.0.2.1.dist-info/RECORD
