Metadata-Version: 2.3
Name: django_no_hot_reload_mod
Version: 0.0.2.1
Summary: Change django endpoints' functionality with no hot reload.
Project-URL: Homepage, https://github.com/AggelosAr/django-no-hot-reload-mod
Project-URL: Issues, https://github.com/AggelosAr/django-no-hot-reload-mod
Author-email: "https://github.com/AggelosAr" <aggelosarelakis@gmail.com>
Classifier: License :: OSI Approved :: MIT License
Classifier: Operating System :: OS Independent
Classifier: Programming Language :: Python :: 3
Requires-Python: >=3.8
